{
    "url": "rtmp://localhost:1935/live",
    "stream_key": "79fe04b7-3235-4bd5-96ea-712b5cf9bbc1",
    "width": 1280,
    "height": 720,
    "fps": 30,
    "gop": 15,
    "codec": "h264",
    "bitrate": 2000000,
    "profile": "baseline",
    "enable_record": true,
    "record_output_dir": "./recordings",
    "record_segment_seconds": 60,
    "record_min_free_percent": 15,
    "record_target_free_percent": 20,
    "record_thumbnail": true,
    "control_enable": true,
    "control_host": "0.0.0.0",
    "control_port": 8090,
    "replay_rtmp_base": "rtmp://localhost:1935/history",
    "ffmpeg_bin": "ffmpeg",
    "mqtt_enable": true,
    "mqtt_host": "127.0.0.1",
    "mqtt_port": 1883,
    "mqtt_client_id": "reallive-pusher-79fe04b7-3235-4bd5-96ea-712b5cf9bbc1",
    "mqtt_topic_prefix": "reallive/device",
    "mqtt_keepalive_sec": 30,
    "mqtt_command_qos": 1,
    "mqtt_state_qos": 0,
    "mqtt_state_interval_ms": 1000,
    "detect_enable": true,
    "detect_draw_overlay": true,
    "detect_interval_frames": 2,
    "detect_motion_ratio": 0.015,
    "detect_diff_threshold": 22,
    "detect_min_box_area_ratio": 0.006,
    "detect_hold_ms": 700,
    "detect_event_min_interval_ms": 1500,
    "detect_opencv_motion_enable": true,
    "detect_tflite_enable": true,
    "detect_infer_on_motion_only": true,
    "detect_tflite_model": "/home/lz/reallive/model/yolov8n_float16.tflite",
    "detect_tflite_labels": "./models/labels.txt",
    "detect_tflite_input_size": 320,
    "detect_person_score_threshold": 0.4,
    "detect_infer_interval_ms": 200,
    "enable_audio": false,
    "sample_rate": 44100,
    "channels": 1,
    "audio_device": "default"
}
